<?xml version="1.0" encoding="UTF-8" standalone="yes" ?>
<document>
<header>
<doctitle>
 傅青主女科 
</doctitle>
<volume>
 產後編下卷 
 </volume>
<author>
 傅山(青主) 
</author>
<date>
 同治八年, 1869 
</date>
<currentpage>
 text 19b 
 </currentpage>
<first>
 Fu Title Page.xml
</first>
<last>
 Fu Text(5) 19b.xml
</last>
<prev>
 Fu Text(5) 19a.xml 
</prev>
<next>
 0
</next>
<image>
 Fu Text(5) 19b.jpg 
</image>
</header><text>
奇 效 
 <formula> 
 全 當 歸 <sf> 一 錢 五 分 酒 洗 </sf> 真 川 芎 <sf> 一 錢 五 分 </sf> 紫 厚 樸 <sf> 七 分 薑 十 炒 </sf> 兔 絲 子 <sf> 一 錢 五 分 酒 包 </sf> 川 貝 母 <sf> 二 錢 去 心 淨 煎 好 方 和 入 </sf> 枳 殼 <sf> 六 分 麵 炒 </sf> 川 羌 活 <sf> 六 分 </sf> 荊 芥 穩 <sf> 八 分 </sf> 黃 &lt;x> <sf> 八 分 蜜 炙 </sf> 蘄 艾 <sf> 五 分 醋 炒 </sf> 炙 草 <sf> 五 分 </sf> 日 [ 白 ] 芍 <sf> 一 錢 二 分 冬 用 二 錢 酒 炒 </sf> 
 </formula> 
 生 薑 三 片 水 二 鐘 煎 八 分 渣 水 一 鐘 煎 六 分 產 前 空 心 預 服 二 劑 臨 產 隨 時 熱 服 
 此 乃 仙 傳 奇 方 慎 勿 以 庸 醫 輕 加 減 其 分 兩 
 <sf> 按 保 產 無 憂 散 保 產 神 效 方 與 編 首 治 產 秘 驗 良 方 俱 相 同 特 引 論 { 略 } 別 並 存 參 看 可 也 </sf> 
 </text></document>