<?xml version="1.0" encoding="UTF-8" standalone="yes" ?>
<document>
<header>
<doctitle>
 傅青主女科 
</doctitle>
<volume>
 女科下卷 
 </volume>
<author>
 傅山(青主) 
</author>
<date>
 同治八年, 1869 
</date>
<currentpage>
 text 5b 
 </currentpage>
<first>
 Fu Title Page.xml
</first>
<last>
 Fu Text(5) 19b.xml
</last>
<prev>
 Fu Text(2) 5a.xml 
</prev>
<next>
 Fu Text(2) 6a.xml 
</next>
<image>
 Fu Text(2) 5b.jpg 
</image>
</header><text>
計 之 以 錢 大 熱 之 品 計 之 以 分 者 不 過 用 以 引 火 而 非 用 以 壯 火 也 其 深 思 哉 
 妊 娠 子 懸 &lt;x> [ 脅 ] 疼 <sf> 四 十 四 </sf> 
 妊 婦 有 懷 抱 憂 鬱 以 致 胎 動 不 安 兩 &lt;x> [ 脅 ] 悶 而 疼 痛 如 弓 上 弦 人 止 知 是 子 懸 之 病 也 誰 知 是 肝 氣 不 通 乎 夫 養 胎 半 &lt;?> [ 係 ] 於 腎 水 然 非 肝 血 相 助 則 腎 水 實 有 獨 力 難 支 之 勢 故 保 胎 必 滋 腎 水 而 肝 血 斷 不 可 不 顧 使 肝 氣 不 鬱 則 肝 之 氣 不 閉 而 肝 之 血 必 旺 自 然 灌 溉 胞 胎 今 腎 水 而 並 協 養 胎 之 力 今 肝 氣 因 憂 鬱 而 閉 塞 則 胎 無 血 蔭 腎 難 獨 任 而 胎 安 得 不 上 升 以 &lt;x> [ 覓 ] 食 此 乃 鬱 氣 使 然 也 莫 認 為 子 之 欲 自 懸 而 妄 用 泄 子 之 品 則 得 矣 治 法 宜 開 肝 氣 之 鬱 結 &lt;x> [ 補 ] 肝 血 之 燥 乾 則 子 懸 自 定 矣 方 用 
 </text></document>