<?xml version="1.0" encoding="UTF-8" standalone="yes" ?>
<document>
<header>
<doctitle>
 傅青主女科 
</doctitle>
<volume>
產後編上卷
 </volume>
<author>
 傅山(青主) 
</author>
<date>
 同治八年, 1869 
</date>
<currentpage>
 text 21a 
 </currentpage>
<first>
 Fu Title Page.xml
</first>
<last>
 Fu Text(5) 19b.xml
</last>
<prev>
 Fu Text(4) 20b.xml 
</prev>
<next>
 Fu Text(4) 21b.xml 
</next>
<image>
 Fu Text(4) 21a.jpg 
</image>
</header><text>
<marginalia> 
 <sf> 本 棗 仁 用 一 錢 細 下 用 四 分 &lt;x> 參 </sf> 
 </marginalia> 
 食 神 &lt;x> [ 曲 ] 麥 芽 以 消 飯 食 大 便 閉 加 肉 蓯 蓉 一 錢 半 汗 多 加 麻 黃 根 一 錢 驚 悸 加 棗 仁 一 錢 
 天 麻 丸 <sf> 治 產 後 中 風 恍 惚 語 &lt;x> [ 澀 ] 四 肢 不 利 </sf>
<formula> 
 天 麻 <sf> 一 錢 </sf> 防 風 <sf> 一 錢 </sf> 川 芎 <sf> 七 分 </sf> &lt;x> [ 羌 ] 活 <sf> 七 分 </sf> 人 參 遠 志 柏 子 仁 山 藥 麥 冬 <sf> 各 一 錢 </sf> 棗 仁 <sf> 一 兩 </sf> 細 辛 <sf> 一 錢 </sf> 南 星 &lt;x> [ 麴 ] <sf> 八 分 </sf> 石 菖 蒲 <sf> 一 錢 </sf> 研 細 未 煉 蜜 為 </formula>
 丸 辰 砂 為 衣 清 湯 下 六 七 十 丸 
 類 痙 <sf> 第 十 二 </sf> 
 產 後 汗 多 即 變 痙 者 項 強 而 身 反 氣 息 如 絕 宜 速 服 加 減 生 化 湯 
 加 減 生 化 湯 <sf> 專 治 有 汗 變 痙 者 </sf>
<formula> 
 川 芎 麻 黃 根 <sf> 各 一 錢 </sf> 當 歸 <sf> 四 錢 </sf> 桂 枝 <sf> 五 分 </sf> 
 </formula> 
 </text></document>