<?xml version="1.0" encoding="UTF-8" standalone="yes" ?>
<document>
<header>
<doctitle>
 傅青主女科 
</doctitle>
<volume>
 女科下卷 
 </volume>
<author>
 傅山(青主) 
</author>
<date>
 同治八年, 1869 
</date>
<currentpage>
 text 20b 
 </currentpage>
<first>
 Fu Title Page.xml
</first>
<last>
 Fu Text(5) 19b.xml
</last>
<prev>
 Fu Text(2) 20a.xml 
</prev>
<next>
 Fu Text(2) 21a.xml 
</next>
<image>
 Fu Text(2) 20b.jpg 
</image>
</header><text>
沖 於 心 也 但 胞 衣 不 下 瘀 血 未 免 難 行 恐 有 血 暈 之 虞 耳 治 法 仍 宜 大 補 其 氣 血 使 生 血 以 送 胞 衣 則 胎 衣 自 然 潤 滑 潤 滑 則 易 下 生 氣 以 助 生 血 則 血 生 自 然 迅 速 尤 易 催 墮 也 方 用 送 胞 湯 
 <formula> 
 當 歸 <sf> 二 兩 酒 洗 </sf> 川 穹 <sf> 五 錢 </sf> 益 母 草 <sf> 一 兩 </sf> 乳 香 <sf> 一 兩 不 去 油 </sf> 沒 藥 <sf> 一 兩 不 去 油 </sf> 芥 穗 <sf> 三 錢 炒 黑 </sf> 麝 香 <sf> 五 釐 研 另 沖 </sf> 
 </formula> 
 水 煎 服 立 下 此 方 以 芎 歸 補 其 氣 血 以 荊 芥 引 血 歸 經 用 益 母 乳 香 等 藥 遂 瘀 而 下 胞 衣 新 血 既 生 則 舊 血 難 存 氣 旺 上 升 而 瘀 濁 自 降 尚 有 留 滯 之 苦 哉 夫 胞 衣 是 包 兒 之 一 物 非 依 於 子 即 依 於 母 子 生 而 不 隨 子 俱 下 以 子 之 不 可 依 也 故 留 滯 於 腹 若 有 &lt;x> [ 回 ] 順 其 母 之 心 母 胞 雖 已 生 子 而 其 蒂 間 之 氣 原 未 遽 絕 
 </text></document>