<?xml version="1.0" encoding="UTF-8" standalone="yes" ?>
<document>
<header>
<doctitle>
 傅青主女科 
</doctitle>
<volume>
 產後編下卷
 </volume>
<author>
 傅山(青主) 
</author>
<date>
 同治八年, 1869 
</date>
<currentpage>
 text 18b 
 </currentpage>
<first>
 Fu Title Page.xml
</first>
<last>
 Fu Text(5) 19b.xml
</last>
<prev>
 Fu Text(5) 18a.xml 
</prev>
<next>
 Fu Text(5) 19a.xml 
</next>
<image>
 Fu Text(5) 18b.jpg 
</image>
</header><text>
糞 用 蜜 棗 導 之 
 煉 蜜 棗 法 
 用 好 蜜 二 三 兩 火 煉 滾 至 茶 褐 色 先 用 溼 桌 傾 蜜 在 桌 上 用 手 作 如 棗 樣 &lt;x> [ 插 ] 肛 門 待 欲 大 便 去 蜜 棗 方 便 又 方 用 麻 油 口 含 竹 管 人 肛 門 內 吹 油 四 五 口 腹 內 糞 和 即 通 或 豬 膽 亦 可 
 治 產 後 雞 瓜 風 
 <formula> 
 桑 柴 灰 <sf> 三 錢 存 性 </sf> 魚 膠 <sf> 三 錢 炒 </sf> 手 指 甲 <sf> 十 二 個 炒 </sf> 
 </formula> 
 共 為 末 黃 酒 送 下 取 汗 即 愈 
 保 產 無 憂 散 
 <formula> 
 當 歸 <sf> 錢 半 酒 洗 </sf> 川 芎 <sf> 錢 半 </sf> 炒 黑 芥 穗 <sf> 八 分 </sf> 艾 葉 <sf> 七 分 炒 </sf> 麵 炒 枳 殼 <sf> 六 分 </sf> 炙 黃 &lt;x> <sf> 八 分 </sf> 兔 絲 子 <sf> 錢 四 分 酒 炒 </sf> 
 </formula> 
 </text></document>