<?xml version="1.0" encoding="UTF-8" standalone="yes" ?>
<document>
<header>
<doctitle>
 傅青主女科 
</doctitle>
<volume>
 產後編下卷
 </volume>
<author>
 傅山(青主) 
</author>
<date>
 同治八年, 1869 
</date>
<currentpage>
 text 3a 
 </currentpage>
<first>
 Fu Title Page.xml
</first>
<last>
 Fu Text(5) 19b.xml
</last>
<prev>
 Fu Text(5) 2b.xml 
</prev>
<next>
 Fu Text(5) 3b.xml 
</next>
<image>
 Fu Text(5) 3a.jpg 
</image>
</header><text>
<formula> 
 白 朮 <sf> 一 錢 土 炒 </sf> 澤 潟 <sf> 八 分 </sf> 
 </formula> 
 寒 瀉 加 乾 薑 八 分 寒 痛 加 砂 仁 炮 薑 各 八 分 熱 瀉 加 
 連 八 分 瀉 水 腹 痛 米 飲 不 化 加 砂 仁 八 分 麥 芽 山 查 各 一 錢 瀉 有 酸 噯 臭 氣 加 神 &lt;x> [ 麴 ] 砂 仁 各 八 分 脾 氣 久 虛 瀉 出 所 食 物 方 快 以 虛 寒 論 瀉 水 者 加 蒼 朮 一 錢 以 燥 溼 脾 氣 弱 元 氣 虛 必 須 大 補 佐 消 食 清 熱 <cf> &#21364; </cf> 寒 藥 弱 甚 形 色 脫 必 須 第 一 方 參 朮 苓 附 必 用 之 藥 也 諸 瀉 俱 加 升 麻 酒 炒 蓮 子 十 粒 
 完 穀 不 化 <sf> 第 二 十 二 </sf> 
 因 產 後 勞 倦 傷 脾 而 運 轉 稽 遲 也 名 飧 泄 又 飲 食 太 過 脾 胃 受 傷 亦 然 俗 呼 水 穀 痢 是 也 然 產 方 三 日 內 塊 未 消 化 此 脾 胃 衰 弱 參 &lt;x> 朮 未 可 遽 加 且 服 生 化 湯 加 益 
 </text></document>