<?xml version="1.0" encoding="UTF-8" standalone="yes" ?>
<document>
<header>
<doctitle>
 重訂濟陰綱目 
 </doctitle>
<volume>
 第八冊, 卷 14 
 </volume>
<author>
 武 之 望   (叔卿 ) 
</author>
<date>
 清雍正六年, 1728
 </date>
<currentpage>
 text 29a 
 </currentpage>
<first>
 jiyingkangmu v.8 text14 1a.xml
</first>
<last>
 bao sheng sui shi 9b.xml
</last>
<prev>
 jiyingkangmu v.8 text14 28b.xml 
</prev>
<next>
 jiyingkangmu v.8 text14 29b.xml 
</next>
<image>
 jiyingkangmu v.8 text14 29a.jpg 
</image>
</header><text>
<formula>土 瓜 根     漏 蘆 <sf> 各 三 兩 </sf>     通 草 <sf> 四 兩 </sf>     甘 草 <sf> 二 兩 </sf> 
 右 剉 碎 以 水 八 升 ﹐ 煎 取 二 升 ﹐ 分 溫 三 服 ﹐ ○ 一 方 加 桂 心 並 為 末 酒 服 方 寸 七 </formula> 
 
 <marginalia> 
 <sf> 若 為 乳 無 汁 須 以 補 氣 血 為 主 而 此 以 土 瓜 根 桂 心 通 血 脈 有 冷 熱 不 同 全 無 氣 血 之 劑 而 甘 草 一 味 又 起 於 法 外 矣 </sf> 
 </marginalia>
<formula> 
 胡 桃 散     治 婦 人 少 乳 及 乳 汁 不 行 。 
 核 桃 仁 <sf> 去 皮 十 箇 搗 爛 </sf>     穿 山 甲 <sf> 為 末 一 錢 </sf> 
 右 搗 和 一 處 ﹐ 黃 酒 調 服 </formula> 
 
 <formula> 
 皂 角 散     治 乳 汁 不 通 。 及 乳 結 硬 疼 痛 。 
 皂 角 <sf> 燒 粉 </sf>     蛤 粉 
 右 為 末 ﹐ 每 服 二 錢 熱 酒 調 服 ○ 歌 曰 婦 人 吹 乳 意 如 何 。 皂 角 燒 灰 蛤 粉     和 。 熱 酒 一 杯 調 八 字 。 須 臾 核 散 笑 呵 呵 。 </formula> 
 
 <formula> 
 張 氏 方     滋 益 氣 <cf> &#33033; </cf> 榮 衛 。 行 津 液 。 
 </formula></text></document>