<?xml version="1.0" encoding="UTF-8" standalone="yes" ?>
<document>
<header>
<doctitle>
 重訂濟陰綱目 
 </doctitle>
<volume>
 第一冊 
 </volume>
<author>
 武 之 望   (叔卿 ) 
</author>
<date>
 清雍正六年, 1728
 </date>
<currentpage>
 table of contents 14b 
 </currentpage>
<first>
 jiyingkangmu v.1 tp.xml
</first>
<last>
 jiyingkangmu v.1 text1 38b.xml 
</last>
<prev>
 jiyingkangmu v.1 table of contents 14a.xml 
</prev>
<next>
 jiyingkangmu v.1 table of contents 15a.xml 
</next>
<image>
 jiyingkangmu v.1 table of contents 14b.jpg 
</image>
</header><text>
治 宮 冷 不 孕 方 
 調 生 丸 一 <sf> 名 詵 詵 丸     治 衝 任 虛 寒 胎 孕 不 成 成 而 多 墮 </sf> 
 調 氣 暖 宮 丸 
 勝 金 丸 <sf> 即 女 金 丹     治 產 後 失 調 經 遲 帶 下 腰 重 寒 熱 身 瘦 眩 暈 嘔 逆 一 切 雜 症 </sf> 
 白 薇 丸 <sf> 治 月 水 不 利 四 肢 羸 瘦 漸 漸 虛 乏 </sf> 
 白 薇 丸 <sf> 治 無 子 斷 經 上 熱 下 冷 百 病 服 之 踰 年 有 子 </sf> 
 秦 桂 丸 <sf> 治 血 海 久 冷 不 能 孕 育 </sf> 
 艾 附 丸 <sf> 暖 子 宮 胎 產 前 後 各 隨 飲 下 </sf> 
 壬 子 丸 <sf> 此 藥 服 之 不 過 一 月 有 孕 試 效 </sf> 
 盪 胞 湯 <sf> 治 婦 人 全 不 產 育 及 二 三 十 年 不 孕 者 </sf> 
 南 嶽 魏 夫 人 濟 陰 丹 <sf> 治 血 海 虛 冷 久 無 孕 育 及 數 墮 胎 一 切 不 調 崩 漏 </sf> 
 紫 石 英 丸 <sf> 治 子 宮 久 冷 不 孕 及 數 墮 胎 月 候 不 勻 崩 漏 癥 瘕 白 淫 白 帶 </sf> 
 坐 導 藥 <sf> 治 婦 人 全 不 產 及 斷 續 服 前 盪 胞 湯 惡 物 不 盡 用 此 方 </sf> 
 內 藥 續 生 丸 <sf> 同 前 </sf> 
 
 治 痰 塞 不 孕 方 
 丹 溪 植 芝 湯 <sf> 治 婦 人 肥 盛 無 子 以 脂 膜 閉 塞 子 宮 也 宜 服 此 </sf> 
 丹 溪 茂 芝 丸 <sf> 治 同 前 </sf> 
 螽 斯 丸 <sf> 即 秦 桂 丸 無 當 歸 防 風 </sf> 
 消 脂 膜 導 痰 湯 
 </text></document>