<?xml version="1.0" encoding="UTF-8" standalone="yes" ?>
<document>
<header>
<doctitle>
 重訂濟陰綱目 
 </doctitle>
<volume>
 第六冊, 卷 11 
 </volume>
<author>
 武 之 望   (叔卿 ) 
</author>
<date>
 清雍正六年, 1728
 </date>
<currentpage>
 text 1a 
 </currentpage>
<first>
 jiyingkangmu v.6 text10 1a.xml
</first>
<last>
 jiyingkangmu v.6 text11 38b.xml
</last>
<prev>
 jiyingkangmu v.6 text10 23b.xml 
</prev>
<next>
 jiyingkangmu v.6 text11 1b.xml 
</next>
<image>
 jiyingkangmu v.6 text11 1a.jpg 
</image>
</header><text>
濟 陰 綱 目 卷 之 十 一 
 
 關 中     武 之 望 叔 卿 父 輯 著     武 林     張 志 聰 隱 庵 父 訂 正 
 西 陵     汪     淇 憺 漪 子 箋 釋         天 都     查     望 于 周 父 參 閱 
 
 ○ 產 後 上 
 ○ 論 產 後 調 理 法 
 大 全 云 凡 生 產 畢 。 飲 熱 童 便 一 盞 。 不 得 便 臥 。 宜 閉 目 少 坐 。 須 臾 上 { 床 } 。 宜 仰 臥 。 不 宜 側 臥 。 宜 豎 膝 。 未 可 伸 足 。 高 倚 { 床 } 頭 。 厚 鋪 裀 褥 。 遮 圍 四 壁 。 使 無 孔 隙 。 免 致 賊 風 。 及 以 醋 塗 鼻 。 或 用 醋 炭 及 燒 漆 器 。 更 以 手 從 心 &lt;x> 至 臍 下 。 使 惡 露 不 滯 。 如 此 三 日 。 以 防 血 暈 血 逆 。 不 問 腹 痛 不 痛 。 有 病 無 病 。 以 童 便 和 酒 半 盞 溫 服 五 七 服 。 酒 雖 行 血 亦 不 可 多 。 恐 引 血 入 四 肢 。 且 能 昏 暈 。 宜 頻 食 白 粥 少 許 。 一 月 之 後 。 宜 食 
 </text></document>