<?xml version="1.0" encoding="UTF-8" standalone="yes" ?>
<document>
<header>
<doctitle>
 重訂濟陰綱目 
 </doctitle>
<volume>
 第三冊, 卷 4 
 </volume>
<author>
 武 之 望   (叔卿 ) 
</author>
<date>
 清雍正六年, 1728
 </date>
<currentpage>
 text 1b 
 </currentpage>
<first>
 jiyingkangmu v.3 text4 1a.xml
</first>
<last>
 jiyingkangmu v.3 text6 26b.xml 
</last>
<prev>
 jiyingkangmu v.3 text4 1a.xml 
</prev>
<next>
 jiyingkangmu v.3 text4 2a.xml 
</next>
<image>
 jiyingkangmu v.3 text4 1b.jpg 
</image>
</header><text>
風 勞 氣 虛 勞 風 勞 冷 勞 熱 勞 客 熱 等 門 。 未 免 惑 亂 。 後 人 靡 所 適 從 。 今 釐 正 如 左 醫 者 更 參 雜 病 虛 勞 傳 尸 勞 。 二 門 而 用 之 。 則 無 遺 少 之 患 矣 。 
 <marginalia> 
 <sf> 看 
 按 血 風 勞 者 肝 血 虛 而 風 熱 成 勞 也 風 勞 冷 勞 因 虛 乘 襲 日 久 <cf> &#21464; </cf> 成 勞 熱 氣 虛 者 氣 不 足 熱 <cf> 勞 </cf> 者 血 不 足 至 骨 蒸 勞 瘵 大 都 難 治 矣 </sf> 
 </marginalia> 
 
 ○ 論 初 病 大 法 。 
 保 命 集 云 。 治 婦 人 虛 勞 局 中 謂 首 尾 六 合 。 如 大 聖 散 。 熱 地 黃 丸 。 是 治   無 熱 虛 勞 也 。 中 道 藥 。 牡 丹 煎 丸 。 空 心 食 前 人 參 荊 芥 散 。 臨 臥 食 後 。 是 治 有 熱 虛 也 。 
 
 戴 氏 曰 。 有 病 後 血 虛 者 。 有 本 体 血 虛 者 。 其 人 往 來 寒 熱 。 或 五 心 發 熱 。 言 語 無 力 。 面 色 痿 黃 頭 目 昏 暈 。 <cf> &#21464; </cf> 生 諸 疾 。 芎 歸 湯 加 羊 肉 少 許 。 或 十 全 大 補 湯 。 四 物 湯 。 養 <cf> 榮 </cf> 湯 。 服 之 血 虛 而 氣 旺 者 。 宜 抑 氣 湯 。 即 香 附 末 。 
 </text></document>