<?xml version="1.0" encoding="UTF-8" standalone="yes" ?>
<document>
<header>
<doctitle>
 女科輯要 
</doctitle>
<volume>
 上卷 
 </volume>
<author>
 沈又彭(堯封) 
</author>
<date>
 同治一年, 1862 
</date>
<currentpage>
 text 44b 
 </currentpage>
<first>
 Nukejiyao v.1 print date.xml
</first>
<last>
 Nukejiyao v.1 text 62b.xml
</last>
<prev>
 Nukejiyao v.1 text 44a.xml 
</prev>
<next>
 Nukejiyao v.1 text 45a.xml 
</next>
<image>
 Nukejiyao v.1 text 44b.jpg 
</image>
</header><text>
則 不 下 
 
 沈 按 尿 血 小 薊 飲 子 妙 。 
 
 雄 按 懷 孕 屢 漏 之 後 。 氣 血 耗 傷 。 有 遲 至 三 四 十 月 而 生 者 。 若 妊 娠 帶 下 多 主 生 女 。 亦 大 不 然 也 。 吳 醞 香 大 令 五 令 媳 。 素 患 帶 。 婚 後 帶 益 盛 。 繼 漸 汛 愆 。 醫 皆 以 為 帶 所 致 也 久 投 溫 澀 無 效 。 余 診 之 脈 甚 滑 數 。 以 懷 麟 斷 。 清 其 胎 火 而 愈 。 及 期 果 誕 一 子 。 
 
 子 淋         轉 胞 
 杰 按 此 淋 字 與 俗 所 云 赤 淋 淋 字 不 同 。 彼 指 赤 帶 言 係 女 精 。 此 係 指 小 水 言 也 。 
 </text></document>