<?xml version="1.0" encoding="UTF-8" standalone="yes" ?>
<document>
<header>
<doctitle>
 女科輯要 
</doctitle>
<volume>
 下卷 
 </volume>
<author>
 沈又彭(堯封) 
</author>
<date>
 同治一年, 1862 
</date>
<currentpage>
 text 21a 
 </currentpage>
<first>
 Nukejiyao v.2 text 1a.xml
</first>
<last>
 Nukejiyao v.2 text 55b.xml
</last>
<prev>
 Nukejiyao v.2 text 20b.xml 
</prev>
<next>
 Nukejiyao v.2 text 21b.xml 
</next>
<image>
 Nukejiyao v.2 text 21a.jpg 
</image>
</header><text>
受 風 而 成 。 宜 服 此 藥 。 戴 氏 證 治 要 法 名 獨 行 散 賈 似 道 悅 生 隨 抄 呼           為 再 生 丹 。 <sf> 指 迷 方 加 當 歸 等 分 </sf> 
 
   沈 云 丁 丑 三 月 。 練 塘 金 虞 旬 第 四 媳 產 後 變 證 伊 郎 來 請 。 先 述 病 狀 云 上 年 十 月 生 產 甚 健 。 至 十 二 月 初 旬 。 面 上 浮 腫 驅 風 不 應 加 麻 黃 三 帖 。 通 身 脹 腫 小 便 不 利 。 更 用 五 皮 雜 治 反 加 臍 凸 更 用 肉 桂 五 苓 。 小 便 略 通 脹 亦 稍 減 。 續 用 桂 附 八 味 其 腫 漸 消 惟 右 手 足 不 減 。 忽 一   日 口 眼 歪 斜 。 左 手 足 不 舉 舌 不 能 言 。 因 作 血 虛 治 。 變 為 俯 不 得 仰 數 日 後 吐 黑 血 盈 盂 。 吐 後 俯 仰 自 如 。 旬 餘 復 不 能 仰 。 又 吐 黑               
 </text></document>