<?xml version="1.0" encoding="UTF-8" standalone="yes" ?>
<document>
<header>
<doctitle>
 珍存秘方
</doctitle>
<volume>
</volume>
<author>
 不詳 
</author>
<date>
 十九世紀晚期或二十世紀早期 
</date>
<currentpage>
 text 10 
 </currentpage>
<first>
 zhencunmifang 1.xml
</first>
<last>
 zhencunmifang 33.xml
</last>
<prev>
 zhencunmifang 9.xml 
</prev>
<next>
 zhencunmifang 11.xml 
</next>
<image>
 zhencunmifang 10.jpg 
</image>
</header><text>
<formula>木 則 二 錢 防 <cf> &#20016; </cf> <sf> 錢 </sf> 西 <cf> 歸 </cf> <sf> 二 錢 </sf> 車 前 <sf> 二 錢 </sf> 羚 羊 <sf> 五 錢 </sf> 赤 芍 <sf> 三 錢 </sf> 青 相 <sf> 二 錢 </sf> 文 軍 <sf> 錢 </sf>   龍 <cf> 膽 </cf> <sf> 三 錢       </sf> </formula>
 治 婦 女 小 便 勤 出 去 有 尿 洒 不 多 小 腹 疼 
   
   陰 戶 疼 痛 
<formula>   熟 地 <sf> 三 錢 </sf> 益 智 仁 <sf> 去 皮 錢 </sf> 山 葯 <sf> 三 錢 </sf> 萸 肉 <sf> 二 錢 半 </sf> 澤 夕 <sf> 三 錢 </sf>   丹 皮 <sf> 三 錢 </sf> 肉 桂 <sf> 二 錢 </sf> 
 坤 艸 <sf> 二 錢 </sf> 南 回 <sf> 二 錢 </sf> <cf> &#64022; </cf> 苓 <sf> 三 錢 </sf> 焦 術 <sf> 三 錢 </sf> 赤 苓 <sf> 三 錢 </sf> </formula>
 <marginalia> 
 <sf> 孕 婦 不 用 </sf> 
 </marginalia>     
 此 方 治 久 寒 神 效 
 </text></document>